[{"id":"01007E300C12C000","names":["カラドリウス ブレイズ"],"publisher":"モス","releaseDate":20190718,"sizeInBytes":2877628088.32},{"id":"010008C00C12E000","names":["雷電V Director's Cut"],"publisher":"モス","releaseDate":20190725,"sizeInBytes":3919157657.6},{"id":"01005CD013116000","names":["雷電Ⅳ×MIKADO remix"],"publisher":"モス","releaseDate":20210422,"sizeInBytes":962592768},{"id":"010089F015FC4000","names":["雷電Ⅲ ×MIKADO MANIAX"],"publisher":"モス","releaseDate":20230223,"sizeInBytes":1428076625.92},{"id":"010095001D1E8000","names":["雷電NOVA"],"publisher":"モス","releaseDate":20241031,"sizeInBytes":739246080}]