[{"id":"010050D00FE0C000","names":["Portal Dogs"],"publisher":"Brain Connected","releaseDate":20200226,"sizeInBytes":111149056},{"id":"0100E6B018CE0000","names":["WFO World Football Online"],"publisher":"Brain Connected","releaseDate":20230928,"sizeInBytes":258998272},{"id":"01009C201BFE8000","names":["Boomshine Plus"],"publisher":"Brain Connected","releaseDate":20230826,"sizeInBytes":34603008},{"id":"0100F5701F62E000","names":["Malignant Survivors"],"publisher":"Brain Connected","releaseDate":20250306,"sizeInBytes":443547648}]