[{"id":"01003D90058FC000","names":["CrossCode"],"publisher":"Deck 13","releaseDate":20200709,"sizeInBytes":2963527434.24},{"id":"0100E7F00FFB8000","names":["Resolutiion"],"publisher":"Deck 13","releaseDate":20200528,"sizeInBytes":884998144},{"id":"010076E0145A6000","names":["Faraday Protocol"],"publisher":"Deck 13","releaseDate":20210812,"sizeInBytes":3801046056.96},{"id":"01008770162FA000","names":["Rising Lords","領主爭鋒 (Rising Lords)"],"publisher":"Deck 13","releaseDate":20240118,"sizeInBytes":640679936},{"id":"0100C510166F0000","names":["Chained Echoes"],"publisher":"Deck 13","releaseDate":20221208,"sizeInBytes":1148903751.68},{"id":"0100C2E01254C000","names":["Lunistice","ルニスティス"],"publisher":"Deck 13","releaseDate":20221110,"sizeInBytes":857735168},{"id":"0100EF601B038000","names":["Drova","Drova - Forsaken Kin","DROVA"],"publisher":"Deck 13","releaseDate":20241015,"sizeInBytes":3704409292.8}]