[{"id":"010045101A660000","names":["Chain Car Stunt Simulator - 3D Extreme Highway Car Driving Games"],"publisher":"DEZVOLT GAMES","releaseDate":20230126,"sizeInBytes":152043520},{"id":"010012C01A708000","names":["Racing in Car - Night Traffic Highway Driving Games Mechanic Simulator 2023 for Kids"],"publisher":"DEZVOLT GAMES","releaseDate":20230413,"sizeInBytes":676331520},{"id":"0100E7401A77C000","names":["Parkour Jump Adventure - Simulator Stunt Tycoon Escape Kid Super Hero World Games"],"publisher":"DEZVOLT GAMES","releaseDate":20230413,"sizeInBytes":299892736},{"id":"010038001AD72000","names":["Hooligan Simulator - San Gangster Andreas Fight for City, Battle Gangs, Shooter, Police"],"publisher":"DEZVOLT GAMES","releaseDate":20230624,"sizeInBytes":2265595248.64},{"id":"010032401AF0E000","names":["Prison Life Simulator Jail - Gangster Escape Games Scary Architect Battle","Prison Life Simulator Jail - Gangster Escape Games Scary"],"publisher":"DEZVOLT GAMES","releaseDate":20230811,"sizeInBytes":1857573355.52},{"id":"010033601B174000","names":["Subway Simulator - Underground Train Ride Station Ultimate Driving Games"],"publisher":"DEZVOLT GAMES","releaseDate":20230714,"sizeInBytes":3328599654.4},{"id":"0100DE401B2C6000","names":["Anime Sexy Girl Puzzle - Hentai Game History Adventure","Anime Sexy Girl Puzzle - Hentay Game History Adventure"],"publisher":"DEZVOLT GAMES","releaseDate":20230915,"sizeInBytes":746586112},{"id":"010035B01B3CE000","names":["Anime Beauty Girl Puzzle - Love Game History Adventure"],"publisher":"DEZVOLT GAMES","releaseDate":20230609,"sizeInBytes":618659840},{"id":"010085001B4C4000","names":["Wash Simulator - Clean Garage, House, Cars Business Tycoons"],"publisher":"DEZVOLT GAMES","releaseDate":20230805,"sizeInBytes":1889785610.24},{"id":"0100E7101B51A000","names":["Race Boat Simulator - 3D Stunt Racing Driving Ship in Ocean","Race Boat Simulator - 3D Stunt Racing Driving Ship Ocean Action Fly"],"publisher":"DEZVOLT GAMES","releaseDate":20230714,"sizeInBytes":957349888},{"id":"0100B0001B51C000","names":["Car Flipper Simulator 2024 - Car Mechanic, Wash, Car Sale","Car for Sale Simulator 2023 - Car Mechanic, Wash, Car Flipper"],"publisher":"DEZVOLT GAMES","releaseDate":20231024,"sizeInBytes":1610612736},{"id":"010065F01B51E000","names":["The Thief Simulator 2023 - From Crook to Boss"],"publisher":"DEZVOLT GAMES","releaseDate":20230902,"sizeInBytes":3231962890.24},{"id":"0100D9001BAE8000","names":["Raccoon Adventure: Animal City Simulator 3D Farm Super Deluxe","Raccoon Adventure: Animal City Simulator 3D Farm Super Deluxe Games"],"publisher":"DEZVOLT GAMES","releaseDate":20230728,"sizeInBytes":1642824990.72},{"id":"010084001C10A000","names":["Rescue Team 911 Simulator - Ambulance,Police, Firefighter"],"publisher":"DEZVOLT GAMES","releaseDate":20230819,"sizeInBytes":1471026298.88},{"id":"010063201C492000","names":["Hentai Anime Girls Succubus"],"publisher":"DEZVOLT GAMES","releaseDate":20240307,"sizeInBytes":1191853424.64},{"id":"0100C3101CE06000","names":["PAINT PRO for KIDS 0+"],"publisher":"DEZVOLT GAMES","releaseDate":20231003,"sizeInBytes":545259520},{"id":"01008FA01CE08000","names":["Car Parking & Car Driving Simulator 2023"],"publisher":"DEZVOLT GAMES","releaseDate":20231010,"sizeInBytes":1675037245.44},{"id":"0100ED201D01A000","names":["The Love - Date Simulator with Girls"],"publisher":"DEZVOLT GAMES","releaseDate":20231017,"sizeInBytes":266338304},{"id":"010020601D0C4000","names":["AAA PRO CLOCK 2023"],"publisher":"DEZVOLT GAMES","releaseDate":20231107,"sizeInBytes":148897792},{"id":"0100EB401D4D4000","names":["The Gardener Simulator - Plant, Grow, Decorate, Build Sim"],"publisher":"DEZVOLT GAMES","releaseDate":20231228,"sizeInBytes":1846835937.28},{"id":"0100FC501D502000","names":["Furniture Flipper Simulator 2023: Revive, Restoration & Creative Crafting","Furniture Flipper Simulator 2023: Revive, Restoration & Creative"],"publisher":"DEZVOLT GAMES","releaseDate":20231121,"sizeInBytes":509607936},{"id":"0100D1501D506000","names":["Mom Simulator 2023"],"publisher":"DEZVOLT GAMES","releaseDate":20231128,"sizeInBytes":1879048192},{"id":"01007A701D8DE000","names":["Pixel Coloring Paint"],"publisher":"DEZVOLT GAMES","releaseDate":20240113,"sizeInBytes":223346688},{"id":"0100F5D01DA3A000","names":["Brain Memory Training Academy"],"publisher":"DEZVOLT GAMES","releaseDate":20240126,"sizeInBytes":135266304},{"id":"0100F5201DBB8000","names":["Forklift Simulator 2024"],"publisher":"DEZVOLT GAMES","releaseDate":20240209,"sizeInBytes":1395864371.2},{"id":"0100BF301DC1E000","names":["MakOS new operating system"],"publisher":"DEZVOLT GAMES","releaseDate":20240210,"sizeInBytes":206569472},{"id":"0100C6601DCCC000","names":["SUDOKU - GAME FOR KIDS"],"publisher":"DEZVOLT GAMES","releaseDate":20240121,"sizeInBytes":106954752},{"id":"010098301DD18000","names":["Lion Simulator Survival: RPG Animal Battle"],"publisher":"DEZVOLT GAMES","releaseDate":20240225,"sizeInBytes":744488960},{"id":"010039201E0C0000","names":["Crazy Goose Simulator"],"publisher":"DEZVOLT GAMES","releaseDate":20240303,"sizeInBytes":850395136},{"id":"010008601E1CA000","names":["Gunsmith Workshop Simulator"],"publisher":"DEZVOLT GAMES","releaseDate":20240309,"sizeInBytes":873463808},{"id":"0100D7101EA42000","names":["Mars Colonization Expedition: Survival Simulator"],"publisher":"DEZVOLT GAMES","releaseDate":20240602,"sizeInBytes":1471026298.88},{"id":"01001F401EDEE000","names":["Culinary Cooking Master Simulator"],"publisher":"DEZVOLT GAMES","releaseDate":20240511,"sizeInBytes":382730240},{"id":"010063501F25C000","names":["Grass Cutting Simulator: Lawn Mowing Care","Grass Cutting Simulator: Lawn Mooving Care"],"publisher":"DEZVOLT GAMES","releaseDate":20240623,"sizeInBytes":742391808},{"id":"0100E9401F6BC000","names":["Urban Survival Simulator: The Bum's Journey"],"publisher":"DEZVOLT GAMES","releaseDate":20240727,"sizeInBytes":1202590842.88},{"id":"010077F01F7A8000","names":["Bid Battle: Auction War Simulator Storage Hunter"],"publisher":"DEZVOLT GAMES","releaseDate":20240809,"sizeInBytes":888143872},{"id":"0100F4701FF6E000","names":["Gold Digger: The Simulator"],"publisher":"DEZVOLT GAMES","releaseDate":20240908,"sizeInBytes":263192576},{"id":"0100FCB020782000","names":["Basketball Legends 24"],"publisher":"DEZVOLT GAMES","releaseDate":20241227,"sizeInBytes":700448768},{"id":"01001B2021278000","names":["Chained Climb Together"],"publisher":"DEZVOLT GAMES","releaseDate":20250110,"sizeInBytes":958398464},{"id":"0100231021804000","names":["Chained Survive Together"],"publisher":"DEZVOLT GAMES","releaseDate":20250415,"sizeInBytes":985661440}]