[{"id":"01005880063AA000","names":["Violett"],"publisher":"Forever Entertainment","releaseDate":20171026,"sizeInBytes":1159641169.92},{"id":"01000490067AE000","names":["Frederic 2: Evil Strikes Back"],"publisher":"Forever Entertainment","releaseDate":20180201,"sizeInBytes":1986422374.4},{"id":"010079F00671C000","names":["Sparkle 2 EVO"],"publisher":"Forever Entertainment","releaseDate":20171102,"sizeInBytes":498073600},{"id":"0100F210061E8000","names":["Hollow"],"publisher":"Forever Entertainment","releaseDate":20180222,"sizeInBytes":2437393940.48},{"id":"01005B1006988000","names":["Frederic: Resurrection of Music"],"publisher":"Forever Entertainment","releaseDate":20171221,"sizeInBytes":984612864},{"id":"0100976008FBE000","names":["Millie"],"publisher":"Forever Entertainment","releaseDate":20180215,"sizeInBytes":278921216},{"id":"0100465009020000","names":["Qbik"],"publisher":"Forever Entertainment","releaseDate":20180118,"sizeInBytes":173015040},{"id":"0100EA1009022000","names":["Timberman VS"],"publisher":"Forever Entertainment","releaseDate":20180503,"sizeInBytes":211812352},{"id":"0100D82009024000","names":["Goetia"],"publisher":"Forever Entertainment","releaseDate":20180426,"sizeInBytes":2190433320.96},{"id":"01005CB009E20000","names":["Glaive: Brick Breaker"],"publisher":"Forever Entertainment","releaseDate":20180426,"sizeInBytes":559939584},{"id":"0100CD300A1BA000","names":["Zombillie"],"publisher":"Forever Entertainment","releaseDate":20180329,"sizeInBytes":414187520},{"id":"0100F7D00A1BC000","names":["NO THING"],"publisher":"Forever Entertainment","releaseDate":20180322,"sizeInBytes":161480704},{"id":"01005E200A3AC000","names":["Sparkle 3 Genesis"],"publisher":"Forever Entertainment","releaseDate":20180315,"sizeInBytes":297795584},{"id":"0100E4F00AE14000","names":["Sparkle ZERO"],"publisher":"Forever Entertainment","releaseDate":20180426,"sizeInBytes":124780544},{"id":"0100D7000AE6A000","names":["Star Story: The Horizon Escape"],"publisher":"Forever Entertainment","releaseDate":20180712,"sizeInBytes":2673617141.76},{"id":"0100E9A00B0BC000","names":["NoReload Heroes"],"publisher":"Forever Entertainment","releaseDate":20180719,"sizeInBytes":581959680},{"id":"0100A7900B936000","names":["Shut Eye"],"publisher":"Forever Entertainment","releaseDate":20180809,"sizeInBytes":160432128},{"id":"010023100B96E000","names":["Persian Nights: Sands of Wonders"],"publisher":"Forever Entertainment","releaseDate":20180817,"sizeInBytes":706740224},{"id":"0100EDA00BBBE000","names":["Fly O'Clock"],"publisher":"Forever Entertainment","releaseDate":20181025,"sizeInBytes":115343360},{"id":"0100C9F00BC50000","names":["Realpolitiks"],"publisher":"Forever Entertainment","releaseDate":20180830,"sizeInBytes":487587840},{"id":"010061A00AE64000","names":["Tiny Hands Adventure"],"publisher":"Forever Entertainment","releaseDate":20180810,"sizeInBytes":2265595248.64},{"id":"0100DDD00C0EA000","names":["Phantaruk"],"publisher":"Forever Entertainment","releaseDate":20180830,"sizeInBytes":4670776934.4},{"id":"0100D1A00C330000","names":["The Mahjong Huntress"],"publisher":"Forever Entertainment","releaseDate":20180913,"sizeInBytes":285212672},{"id":"01006BE00B3C8000","names":["My Brother Rabbit"],"publisher":"Forever Entertainment","releaseDate":20180921,"sizeInBytes":1116691496.96},{"id":"01000E200C8D4000","names":["Hyperide: Vector Raid"],"publisher":"Forever Entertainment","releaseDate":20181217,"sizeInBytes":347078656},{"id":"0100E4400C9A6000","names":["Diggerman"],"publisher":"Forever Entertainment","releaseDate":20181224,"sizeInBytes":371195904},{"id":"010051D00C9F8000","names":["Startide"],"publisher":"Forever Entertainment","releaseDate":20181025,"sizeInBytes":1027604480},{"id":"0100C0F00CA9C000","names":["IHUGU"],"publisher":"Forever Entertainment","releaseDate":20190121,"sizeInBytes":118489088},{"id":"0100F6200CBE0000","names":["Teddy the Wanderer: Kayaking"],"publisher":"Forever Entertainment","releaseDate":20181115,"sizeInBytes":823132160},{"id":"010091000CC0E000","names":["Hyperide"],"publisher":"Forever Entertainment","releaseDate":20190130,"sizeInBytes":183500800},{"id":"010002A00CC42000","names":["Clock Simulator"],"publisher":"Forever Entertainment","releaseDate":20190110,"sizeInBytes":109051904},{"id":"01005AF00CCA2000","names":["Risky Rescue"],"publisher":"Forever Entertainment","releaseDate":20190418,"sizeInBytes":234881024},{"id":"0100ACF00CD2E000","names":["Robothorium"],"publisher":"Forever Entertainment","releaseDate":20190131,"sizeInBytes":1234803097.6},{"id":"0100CEB00CD6C000","names":["Surfingers"],"publisher":"Forever Entertainment","releaseDate":20190221,"sizeInBytes":216006656},{"id":"01008E500CF02000","names":["Estiman"],"publisher":"Forever Entertainment","releaseDate":20190207,"sizeInBytes":146800640},{"id":"0100A6C00CF70000","names":["Grab Lab"],"publisher":"Forever Entertainment","releaseDate":20190110,"sizeInBytes":360710144},{"id":"01000CB00D094000","names":["Bad Dream: Coma"],"publisher":"Forever Entertainment","releaseDate":20190124,"sizeInBytes":377487360},{"id":"0100ECE00D13E000","names":["Hard West"],"publisher":"Forever Entertainment","releaseDate":20190307,"sizeInBytes":6077378723.84},{"id":"010072600D21C000","names":["Agony"],"publisher":"Forever Entertainment","releaseDate":20191031,"sizeInBytes":8257074626.56},{"id":"010069800D292000","names":["Fishing Universe Simulator"],"publisher":"Forever Entertainment","releaseDate":20190124,"sizeInBytes":1438814044.16},{"id":"01001D600D2C8000","names":["Bedtime Blues"],"publisher":"Forever Entertainment","releaseDate":20190117,"sizeInBytes":418381824},{"id":"0100E5000D3CA000","names":["Merchants of Kaidan"],"publisher":"Forever Entertainment","releaseDate":20190131,"sizeInBytes":1825361100.8},{"id":"0100EDD00D530000","names":["Nice Slice"],"publisher":"Forever Entertainment","releaseDate":20190214,"sizeInBytes":428867584},{"id":"010032800D46C000","names":["Dungeons & Aliens"],"publisher":"Forever Entertainment","releaseDate":20190315,"sizeInBytes":174063616},{"id":"0100B3B00D81C000","names":["Bad Dream: Fever"],"publisher":"Forever Entertainment","releaseDate":20190314,"sizeInBytes":408944640},{"id":"010078300DA14000","names":["Teddy The Wanderer: Mountain Hike"],"publisher":"Forever Entertainment","releaseDate":20190314,"sizeInBytes":1042284544},{"id":"0100F0A00C2F2000","names":["Assault On Metaltron"],"publisher":"Forever Entertainment","releaseDate":20190320,"sizeInBytes":456130560},{"id":"0100CE400E34E000","names":["Thief Simulator"],"publisher":"Forever Entertainment","releaseDate":20190516,"sizeInBytes":3189013217.28},{"id":"010096F00E5B0000","names":["Phantom Doctrine"],"publisher":"Forever Entertainment","releaseDate":20190606,"sizeInBytes":7075958620.16},{"id":"0100F1100E606000","names":["Q-YO Blaster"],"publisher":"Forever Entertainment","releaseDate":20190627,"sizeInBytes":209715200},{"id":"010062900E610000","names":["Towaga: Among Shadows","TOWAGA ー深淵の影ー"],"publisher":"Forever Entertainment","releaseDate":20200625,"sizeInBytes":1363652116.48},{"id":"0100C6A00E94A000","names":["Panzer Dragoon: Remake"],"publisher":"Forever Entertainment","releaseDate":20200326,"sizeInBytes":9706626088.96},{"id":"010066800E9F8000","names":["The Childs Sight"],"publisher":"Forever Entertainment","releaseDate":20190620,"sizeInBytes":963641344},{"id":"010030D00EA1C000","names":["Sparkle 4 Tales"],"publisher":"Forever Entertainment","releaseDate":20200130,"sizeInBytes":638582784},{"id":"01000A600EA88000","names":["Grave Keeper"],"publisher":"Forever Entertainment","releaseDate":20190808,"sizeInBytes":471859200},{"id":"010043700EB68000","names":["TERRORHYTHM (TRRT)"],"publisher":"Forever Entertainment","releaseDate":20190808,"sizeInBytes":492830720},{"id":"01001D500EB90000","names":["Omen Exitio: Plague"],"publisher":"Forever Entertainment","releaseDate":20190829,"sizeInBytes":1224065679.36},{"id":"010050E00EC8E000","names":["Gunpowder on The Teeth: Arcade"],"publisher":"Forever Entertainment","releaseDate":20190725,"sizeInBytes":113246208},{"id":"0100EBC00ECA8000","names":["Tap Skaters","タップスケーターズ"],"publisher":"Forever Entertainment","releaseDate":20190808,"sizeInBytes":355467264},{"id":"0100D3300F110000","names":["Mr Blaster"],"publisher":"Forever Entertainment","releaseDate":20190822,"sizeInBytes":567279616},{"id":"0100B8800F858000","names":["Sinless"],"publisher":"Forever Entertainment","releaseDate":20200123,"sizeInBytes":2287070085.12},{"id":"010048000F946000","names":["Masky"],"publisher":"Forever Entertainment","releaseDate":20200611,"sizeInBytes":150994944},{"id":"01000C800FADC000","names":["Go All Out!"],"publisher":"Forever Entertainment","releaseDate":20200213,"sizeInBytes":2619930050.56},{"id":"01007FB00FC5E000","names":["Dark Veer"],"publisher":"Forever Entertainment","releaseDate":20191024,"sizeInBytes":363855872},{"id":"0100B7200FC96000","names":["Roll'd"],"publisher":"Forever Entertainment","releaseDate":20191226,"sizeInBytes":454033408},{"id":"01001E400FD58000","names":["Cooking Simulator"],"publisher":"Forever Entertainment","releaseDate":20200514,"sizeInBytes":2276332666.88},{"id":"0100AEC010052000","names":["Biolab Wars"],"publisher":"Forever Entertainment","releaseDate":20191115,"sizeInBytes":209715200},{"id":"0100B27010436000","names":["Wanderlust Travel Stories"],"publisher":"Forever Entertainment","releaseDate":20200227,"sizeInBytes":1589137899.52},{"id":"0100AC40108D8000","names":["Fred3ric"],"publisher":"Forever Entertainment","releaseDate":20200220,"sizeInBytes":1782411427.84},{"id":"0100395010AD2000","names":["OmoTomO"],"publisher":"Forever Entertainment","releaseDate":20200123,"sizeInBytes":800063488},{"id":"01006B601117E000","names":["Ultimate Ski Jumping 2020","アルティメットスキージャンプ 2021"],"publisher":"Forever Entertainment","releaseDate":20200319,"sizeInBytes":2985002270.72},{"id":"01001F70112BA000","names":["Poly Puzzle"],"publisher":"Forever Entertainment","releaseDate":20200312,"sizeInBytes":167772160},{"id":"010001C011354000","names":["Aeolis Tournament"],"publisher":"Forever Entertainment","releaseDate":20200723,"sizeInBytes":1277752770.56},{"id":"0100BEE011402000","names":["Pack Master"],"publisher":"Forever Entertainment","releaseDate":20200611,"sizeInBytes":72351744},{"id":"0100459011750000","names":["Tennis Open 2020"],"publisher":"Forever Entertainment","releaseDate":20200319,"sizeInBytes":205520896},{"id":"01000580117EA000","names":["Seeds of Resilience"],"publisher":"Forever Entertainment","releaseDate":20200611,"sizeInBytes":416284672},{"id":"01005F2011F8C000","names":["Pixboy"],"publisher":"Forever Entertainment","releaseDate":20200611,"sizeInBytes":205520896},{"id":"0100DB80123D2000","names":["Hot Shot Burn"],"publisher":"Forever Entertainment","releaseDate":20201001,"sizeInBytes":1428076625.92},{"id":"0100861012474000","names":["Frontline Zed","FRONTLINE ZED"],"publisher":"Forever Entertainment","releaseDate":20200806,"sizeInBytes":3156800962.56},{"id":"010050C0124CE000","names":["Mini Island Challenge Bundle"],"publisher":"Forever Entertainment","releaseDate":20200723,"sizeInBytes":763363328},{"id":"01005D701264A000","names":["SpyHack"],"publisher":"Forever Entertainment","releaseDate":20200716,"sizeInBytes":1954210119.68},{"id":"0100A1F012948000","names":["Bomber Fox"],"publisher":"Forever Entertainment","releaseDate":20200917,"sizeInBytes":1385126952.96},{"id":"010048901295C000","names":["Ultimate Fishing Simulator","アルティメット フィッシング シミュレータ"],"publisher":"Forever Entertainment","releaseDate":20200827,"sizeInBytes":4144643440.64},{"id":"0100453012FEA000","names":["Green Hell"],"publisher":"Forever Entertainment","releaseDate":20201008,"sizeInBytes":2426656522.24},{"id":"0100489013A3C000","names":["VIRUS: The Outbreak"],"publisher":"Forever Entertainment","releaseDate":20201228,"sizeInBytes":2179695902.72},{"id":"0100CFB013AE4000","names":["Binarystar Infinity"],"publisher":"Forever Entertainment","releaseDate":20210204,"sizeInBytes":75497472},{"id":"01002FB013B8E000","names":["The Dealer Simulator"],"publisher":"Forever Entertainment","releaseDate":20210311,"sizeInBytes":1159641169.92},{"id":"0100EFA013E7C000","names":["Danger Scavenger","デンジャー スカベンジャー"],"publisher":"Forever Entertainment","releaseDate":20210325,"sizeInBytes":2351494594.56},{"id":"010046D013EB6000","names":["Project AETHER: First Contact"],"publisher":"Forever Entertainment","releaseDate":20210805,"sizeInBytes":1406601789.44},{"id":"0100DF8014056000","names":["Aery – A Journey Beyond Time","Aery - A Journey Beyond Time","ザフライーングトラベラージャーニービヨンドタイム"],"publisher":"Forever Entertainment","releaseDate":20210225,"sizeInBytes":3242700308.48},{"id":"01006A90144E4000","names":["A Long Way Down"],"publisher":"Forever Entertainment","releaseDate":20210401,"sizeInBytes":1513975971.84},{"id":"010077B014518000","names":["Stitchy in Tooki Trouble"],"publisher":"Forever Entertainment","releaseDate":20210415,"sizeInBytes":2372969431.04},{"id":"0100B38013F66000","names":["Neurodeck"],"publisher":"Forever Entertainment","releaseDate":20211118,"sizeInBytes":528482304},{"id":"010088401495E000","names":["THE HOUSE OF THE DEAD: Remake"],"publisher":"Forever Entertainment","releaseDate":20220407,"sizeInBytes":3575560273.92},{"id":"0100C670149D4000","names":["Train Station Renovation","Bienvenue dans une ancienne gare en ruine. Un endroit qui te procurera beaucoup de plaisir !"],"publisher":"Forever Entertainment","releaseDate":20210506,"sizeInBytes":4595615006.72},{"id":"010015F014A5C000","names":["Rise Eterna","ライズ・エテルナ"],"publisher":"Forever Entertainment","releaseDate":20210513,"sizeInBytes":2254857830.4},{"id":"0100FF5015416000","names":["Smashroom"],"publisher":"Forever Entertainment","releaseDate":20210805,"sizeInBytes":141557760},{"id":"010017E015636000","names":["Barbero"],"publisher":"Forever Entertainment","releaseDate":20211014,"sizeInBytes":201326592},{"id":"0100D8C01674C000","names":["Pawn of the Dead"],"publisher":"Forever Entertainment","releaseDate":20211230,"sizeInBytes":1202590842.88},{"id":"0100402016908000","names":["Baby Storm","Baby Storm (寶寶鬧翻天)"],"publisher":"Forever Entertainment","releaseDate":20220121,"sizeInBytes":2652142305.28},{"id":"0100BF1016A66000","names":["Armed to the Gears"],"publisher":"Forever Entertainment","releaseDate":20211125,"sizeInBytes":776994816},{"id":"0100E21016A68000","names":["Blocky Farm"],"publisher":"Forever Entertainment","releaseDate":20230316,"sizeInBytes":430964736},{"id":"0100326016A6E000","names":["Wax Museum"],"publisher":"Forever Entertainment","releaseDate":20211118,"sizeInBytes":704643072},{"id":"01007DE016E9E000","names":["Hollow 2"],"publisher":"Forever Entertainment","releaseDate":20211230,"sizeInBytes":3285649981.44},{"id":"0100D76017804000","names":["Dino Galaxy Tennis"],"publisher":"Forever Entertainment","releaseDate":20220210,"sizeInBytes":516947968},{"id":"0100F200178F4000","names":["FRONT MISSION 1st: Remake","フロントミッション　ザ・ファースト: リメイク"],"publisher":"Forever Entertainment","releaseDate":20221130,"sizeInBytes":6635724472.32},{"id":"010067F017FF6000","names":["Goetia 2"],"publisher":"Forever Entertainment","releaseDate":20220519,"sizeInBytes":1224065679.36},{"id":"01004450181D8000","names":["Criminal Expert"],"publisher":"Forever Entertainment","releaseDate":20220825,"sizeInBytes":4176855695.36},{"id":"01004B90183A4000","names":["Timberman: The Big Adventure","ティンバーマン：ザ・ビッグ・アドベンチャー"],"publisher":"Forever Entertainment","releaseDate":20220818,"sizeInBytes":461373440},{"id":"0100C4E018A24000","names":["FRONT MISSION 2: Remake","フロントミッション セカンド:リメイク"],"publisher":"Forever Entertainment","releaseDate":20231005,"sizeInBytes":7827577896.96},{"id":"0100DBA0193F6000","names":["Milk inside a bag of milk inside a bag of milk and Milk outside a bag of milk outside a bag of milk"],"publisher":"Forever Entertainment","releaseDate":20221111,"sizeInBytes":553648128},{"id":"010036C01960E000","names":["Aircraft Carrier Survival"],"publisher":"Forever Entertainment","releaseDate":20221229,"sizeInBytes":4294967296},{"id":"01007E6019872000","names":["FRONT MISSION 3: Remake","フロントミッション サード: リメイク"],"publisher":"Forever Entertainment","releaseDate":20250626,"sizeInBytes":5025111736.32},{"id":"0100A55019C38000","names":["Fishing: North Atlantic"],"publisher":"Forever Entertainment","releaseDate":20230323,"sizeInBytes":8568459755.52},{"id":"0100B4D01A3A4000","names":["Magical Drop VI","マジカルドロップ6"],"publisher":"Forever Entertainment","releaseDate":20230425,"sizeInBytes":926941184},{"id":"010060101A6E0000","names":["Alekon"],"publisher":"Forever Entertainment","releaseDate":20230406,"sizeInBytes":1513975971.84},{"id":"0100DB101B90E000","names":["Until The Last Bullet"],"publisher":"Forever Entertainment","releaseDate":20231116,"sizeInBytes":2662879723.52},{"id":"010079101D092000","names":["UNABLES"],"publisher":"Forever Entertainment","releaseDate":20240314,"sizeInBytes":1288490188.8},{"id":"010022201D254000","names":["Flooded"],"publisher":"Forever Entertainment","releaseDate":20231109,"sizeInBytes":653262848},{"id":"010005E01E5E6000","names":["Hero's Hour"],"publisher":"Forever Entertainment","releaseDate":20240411,"sizeInBytes":510656512},{"id":"0100BD301E8B0000","names":["Overboss"],"publisher":"Forever Entertainment","releaseDate":20240815,"sizeInBytes":1395864371.2},{"id":"0100F1501EF3E000","names":["Rise Eterna War"],"publisher":"Forever Entertainment","releaseDate":20240822,"sizeInBytes":1034944512},{"id":"010093801FECE000","names":["Night Slashers: Remake"],"publisher":"Forever Entertainment","releaseDate":20240926,"sizeInBytes":1309965025.28},{"id":"0100891020682000","names":["Care Bears: To The Rescue","ケアベア　トゥ・ザ・レスキュー"],"publisher":"Forever Entertainment","releaseDate":20241024,"sizeInBytes":676331520},{"id":"01004590216DC000","names":["Blue Wednesday"],"publisher":"Forever Entertainment","releaseDate":20250327,"sizeInBytes":1503238553.6},{"id":"0100BDB020F62000","names":["Fiz and the Rainbow Planet","フィズとにじいろの星"],"publisher":"Forever Entertainment","releaseDate":20250710,"sizeInBytes":1245540515.84},{"id":"010016900AD24000","names":["進化のひみつ","스파클 2: EVO"],"publisher":"Forever Entertainment","releaseDate":20180517,"sizeInBytes":385875968},{"id":"010058700C36C000","names":["Hollow (ホロウ)"],"publisher":"Forever Entertainment","releaseDate":20181206,"sizeInBytes":2372969431.04},{"id":"01005F200C36E000","names":["ティンバーマン VS エディション"],"publisher":"Forever Entertainment","releaseDate":20181101,"sizeInBytes":212860928},{"id":"010013A00EA0C000","names":["進化のひみつ ZERO"],"publisher":"Forever Entertainment","releaseDate":20190627,"sizeInBytes":170917888},{"id":"010081F00EAB8000","names":["キュービック"],"publisher":"Forever Entertainment","releaseDate":20190704,"sizeInBytes":118489088},{"id":"0100B4900EFAC000","names":["バランスさがし"],"publisher":"Forever Entertainment","releaseDate":20190801,"sizeInBytes":322961408},{"id":"0100C4B00F22A000","names":["進化のひみつ  生命のはじまり"],"publisher":"Forever Entertainment","releaseDate":20190926,"sizeInBytes":368050176},{"id":"0100BF500FBB4000","names":["リスキーレスキュー"],"publisher":"Forever Entertainment","releaseDate":20191219,"sizeInBytes":242221056},{"id":"0100F0B00FBB8000","names":["フィンガーサーファー"],"publisher":"Forever Entertainment","releaseDate":20191219,"sizeInBytes":214958080},{"id":"010070D00FBE4000","names":["ショパンの復活　音楽を救え！"],"publisher":"Forever Entertainment","releaseDate":20191017,"sizeInBytes":558891008},{"id":"01007EE00FC58000","names":["ショパンの復活　悪魔の逆襲！"],"publisher":"Forever Entertainment","releaseDate":20191107,"sizeInBytes":1997159792.64},{"id":"01004A000FCD8000","names":["バイオレットと奇妙な世界","Violett"],"publisher":"Forever Entertainment","releaseDate":20191219,"sizeInBytes":1642824990.72},{"id":"01000B700FF6A000","names":["チャイルド・サイト"],"publisher":"Forever Entertainment","releaseDate":20200213,"sizeInBytes":1127428915.2},{"id":"0100D730105B6000","names":["ノーリロードヒーローズ"],"publisher":"Forever Entertainment","releaseDate":20191219,"sizeInBytes":476053504},{"id":"0100B9A010B36000","names":["NO THING"],"publisher":"Forever Entertainment","releaseDate":20200130,"sizeInBytes":354418688},{"id":"01009C5011274000","names":["Fly O’Clock VS エディション"],"publisher":"Forever Entertainment","releaseDate":20200409,"sizeInBytes":118489088},{"id":"010081A011276000","names":["Q-YO Blaster"],"publisher":"Forever Entertainment","releaseDate":20200409,"sizeInBytes":285212672},{"id":"01005B2011826000","names":["テラービートリズム"],"publisher":"Forever Entertainment","releaseDate":20200827,"sizeInBytes":507510784},{"id":"0100BA2011A5E000","names":["ノー グラビティ ラボ"],"publisher":"Forever Entertainment","releaseDate":20200430,"sizeInBytes":338690048},{"id":"0100ACB011A82000","names":["ガンパウダー"],"publisher":"Forever Entertainment","releaseDate":20200430,"sizeInBytes":85983232},{"id":"010001C011BBA000","names":["パンツァードラグーン：リメイク"],"publisher":"Forever Entertainment","releaseDate":20200402,"sizeInBytes":9459665469.44},{"id":"0100FB9011D02000","names":["ディガーマン"],"publisher":"Forever Entertainment","releaseDate":20200430,"sizeInBytes":308281344},{"id":"01004D00123A8000","names":["テディの冒険　ハイキングに行こう！"],"publisher":"Forever Entertainment","releaseDate":20210318,"sizeInBytes":396361728},{"id":"01000B401284E000","names":["ポリーパズル"],"publisher":"Forever Entertainment","releaseDate":20200827,"sizeInBytes":69206016},{"id":"0100B4F0128E2000","names":["パッキングマスター"],"publisher":"Forever Entertainment","releaseDate":20200827,"sizeInBytes":75497472},{"id":"0100D1A012B6A000","names":["ミスターブラスター"],"publisher":"Forever Entertainment","releaseDate":20201203,"sizeInBytes":583008256},{"id":"0100820012B6C000","names":["ドットボーイ"],"publisher":"Forever Entertainment","releaseDate":20201203,"sizeInBytes":123731968},{"id":"0100581012D30000","names":["マスクド チェーン ダンス"],"publisher":"Forever Entertainment","releaseDate":20201203,"sizeInBytes":163577856},{"id":"0100354012E7C000","names":["テニス オープン 2020"],"publisher":"Forever Entertainment","releaseDate":20201203,"sizeInBytes":118489088},{"id":"01008B70135A2000","names":["ミリーのモンスターメイズ"],"publisher":"Forever Entertainment","releaseDate":20201203,"sizeInBytes":384827392},{"id":"0100FAB0135A6000","names":["ミリーのメイズ"],"publisher":"Forever Entertainment","releaseDate":20201203,"sizeInBytes":493879296},{"id":"0100C8D01392C000","names":["GREEN HELL"],"publisher":"Forever Entertainment","releaseDate":20210210,"sizeInBytes":1814623682.56},{"id":"0100BE5013B4C000","names":["泥棒シミュレーター"],"publisher":"Forever Entertainment","releaseDate":20201203,"sizeInBytes":2222645575.68},{"id":"01004C0013DBE000","names":["クローズドアイ"],"publisher":"Forever Entertainment","releaseDate":20210318,"sizeInBytes":350224384},{"id":"01000CC013E42000","names":["バイナリースターインフィニティ"],"publisher":"Forever Entertainment","releaseDate":20210204,"sizeInBytes":75497472},{"id":"0100A37014230000","names":["ショパンの復活 3"],"publisher":"Forever Entertainment","releaseDate":20210318,"sizeInBytes":1932735283.2},{"id":"01003F8014284000","names":["クッキングシミュレーター"],"publisher":"Forever Entertainment","releaseDate":20210311,"sizeInBytes":1288490188.8},{"id":"0100B3A017864000","names":["ザ・ハウス・オブ・ザ・デッド：リメイク"],"publisher":"Forever Entertainment","releaseDate":20220407,"sizeInBytes":3575560273.92},{"id":"01002CC019BE6000","names":["ザ・ハウス・オブ・ザ・デッド：リメイク Zバージョン"],"publisher":"Forever Entertainment","releaseDate":20230615,"sizeInBytes":3307124817.92},{"id":"01001EA01FC06000","names":["UNABLES"],"publisher":"Forever Entertainment","releaseDate":20240801,"sizeInBytes":1460288880.64}]