[{"id":"01002DF00F76C000","names":["SAMURAI SHODOWN"],"publisher":"SNK","releaseDate":20200225,"sizeInBytes":16181289287.68},{"id":"010095300F778000","names":["SAMURAI SHODOWN!2","サムライスピリッツ！2"],"publisher":"SNK","releaseDate":20200807,"sizeInBytes":150994944},{"id":"01007EE011116000","names":["SNK GALS' FIGHTERS"],"publisher":"SNK","releaseDate":20200429,"sizeInBytes":136314880},{"id":"0100F6800F48E000","names":["SAMURAI SHODOWN NEOGEO COLLECTION","サムライスピリッツ ネオジオコレクション"],"publisher":"SNK","releaseDate":20200728,"sizeInBytes":7473243095.04},{"id":"0100D47012330000","names":["KING OF FIGHTERS R-2","キング・オブ・ファイターズ R-2"],"publisher":"SNK","releaseDate":20200807,"sizeInBytes":95420416},{"id":"010006D0128B4000","names":["NEOGEO POCKET COLOR SELECTION Vol.1"],"publisher":"SNK","releaseDate":20210317,"sizeInBytes":1084479242.24},{"id":"0100A35012908000","names":["THE LAST BLADE: Beyond the Destiny","幕末浪漫特別編 月華の剣士 ～月に咲く華、散りゆく花～"],"publisher":"SNK","releaseDate":20201028,"sizeInBytes":155189248},{"id":"010059B012E60000","names":["FATAL FURY FIRST CONTACT","餓狼伝説ファーストコンタクト"],"publisher":"SNK","releaseDate":20201223,"sizeInBytes":154140672},{"id":"0100F2B012E62000","names":["\"METAL SLUG 1st & 2nd MISSION\" Double Pack","メタルスラッグ ファースト&セカンドミッション ダブルパック","『METAL SLUG 1st & 2nd MISSION』同捆包（Double Pack）"],"publisher":"SNK","releaseDate":20210915,"sizeInBytes":131072000},{"id":"0100F35012E64000","names":["METAL SLUG 2ND MISSION","メタルスラッグ セカンドミッション"],"publisher":"SNK","releaseDate":20210915,"sizeInBytes":73400320},{"id":"010027D0137E0000","names":["SNK VS. CAPCOM: THE MATCH OF THE MILLENNIUM","頂上決戦 最強ファイターズ SNK VS. CAPCOM"],"publisher":"SNK","releaseDate":20210217,"sizeInBytes":223346688},{"id":"0100D8D0160C6000","names":["NEOGEO POCKET COLOR SELECTION Vol.2"],"publisher":"SNK","releaseDate":20221109,"sizeInBytes":1037041664},{"id":"010019F016134000","names":["SNK VS. CAPCOM: CARD FIGHTERS' CLASH","SNK VS. CAPCOM 激突カードファイターズ"],"publisher":"SNK","releaseDate":20220112,"sizeInBytes":244318208},{"id":"0100C68016136000","names":["BIOMOTOR UNITRON","バイオモーター・ユニトロン"],"publisher":"SNK","releaseDate":20220525,"sizeInBytes":148897792},{"id":"01004CB01613A000","names":["BIG BANG PRO WRESTLING","ビッグバンプロレス"],"publisher":"SNK","releaseDate":20220330,"sizeInBytes":168820736},{"id":"01003DF018D5A000","names":["MEGA MAN BATTLE & FIGHTERS","ロックマン バトル＆ファイターズ"],"publisher":"SNK","releaseDate":20220803,"sizeInBytes":114294784},{"id":"0100DC701A388000","names":["THE KING OF FIGHTERS XIII GLOBAL MATCH","THE KING OF FIGHTERS XIII GLOBAL MATCH Standard Edition"],"publisher":"SNK","releaseDate":20231116,"sizeInBytes":3210488053.76},{"id":"010073401B8DE000","names":["METAL SLUG ATTACK RELOADED"],"publisher":"SNK","releaseDate":20240618,"sizeInBytes":1836098519.04},{"id":"01007AD01C432000","names":["SNK VS. CAPCOM SVC CHAOS"],"publisher":"SNK","releaseDate":20240722,"sizeInBytes":288358400},{"id":"010036101CD98000","names":["THE KING OF FIGHTERS XIII GLOBAL MATCH Artbook & Soundtrack"],"publisher":"SNK","releaseDate":20231116,"sizeInBytes":266338304},{"id":"01005ED00AD0C000","names":["SNKヒロインズ Tag Team Frenzy"],"publisher":"SNK","releaseDate":20180906,"sizeInBytes":16095389941.76},{"id":"01008FC00D964000","names":["SAMURAI SPIRITS","SAMURAI SHODOWN"],"publisher":"SNK","releaseDate":20191212,"sizeInBytes":16181289287.68},{"id":"01008FE01E0C2000","names":["METAL SLUG TACTICS"],"publisher":"SNK","releaseDate":20241105,"sizeInBytes":1513975971.84}]