[{"id":"010097600C322000","names":["ANIMUS"],"publisher":"TROOOZE","releaseDate":20190103,"sizeInBytes":2856153251.84},{"id":"010029400DE76000","names":["Bullet Battle: Evolution"],"publisher":"TROOOZE","releaseDate":20190606,"sizeInBytes":614465536},{"id":"0100E5A00FD38000","names":["ANIMUS: Harbinger"],"publisher":"TROOOZE","releaseDate":20191107,"sizeInBytes":2233382993.92},{"id":"0100CAB012FCC000","names":["Dungeon Limbus","ダンジョンリンバス","던전 림버스(Dungeon Limbus)","地下城邊緣(Dungeon Limbus)"],"publisher":"TROOOZE","releaseDate":20201228,"sizeInBytes":390070272},{"id":"010000401313A000","names":["Demong Hunter","데몽 헌터(Demong Hunter)"],"publisher":"TROOOZE","releaseDate":20201029,"sizeInBytes":339738624},{"id":"010005A0143CC000","names":["Counter Recon: The First Mission","カウンターリーコン ザ・ファーストミッション","카운터리콘 더 퍼스트 미션(Counter Recon: The First Mission)","反偵察: 第壹任務(Counter Recon: The First Mission)"],"publisher":"TROOOZE","releaseDate":20210304,"sizeInBytes":2684354560},{"id":"0100C88014614000","names":["Dark Water: Slime Invader","ダークウォーター スライム・インベーダー","黑水: 史萊姆侵入者(Dark Water: Slime Invader)"],"publisher":"TROOOZE","releaseDate":20210318,"sizeInBytes":1395864371.2},{"id":"01009E6014F18000","names":["Haunted Dawn: The Zombie Apocalypse","ホーンテッドドーン ザ・ゾンビ アポカリプス","헌티드던 더 좀비 아포칼립스(Haunted Dawn: The Zombie Apocalypse)","鬼魂黎明: 僵屍啟示錄(Haunted Dawn: The Zombie Apocalypse)"],"publisher":"TROOOZE","releaseDate":20210603,"sizeInBytes":8031588843.52},{"id":"01009C60152B6000","names":["ANIMUS: Revenant","アニマス レヴェナント","애니머스 레버넌트(ANIMUS: Revenant)","憎恨之心: 亡者歸來(ANIMUS: Revenant)"],"publisher":"TROOOZE","releaseDate":20210610,"sizeInBytes":2695091978.24},{"id":"0100C1C0158F2000","names":["Girls Tank Battle","ガールズタンクバトル","걸즈 탱크 배틀(Girls Tank Battle)","少女坦克大戰(Girls Tank Battle)"],"publisher":"TROOOZE","releaseDate":20210826,"sizeInBytes":369098752},{"id":"0100C6101591A000","names":["Last 4 Alive: Escape From Zombies","ラスト4アライブ ゾンビからの脱出","라스트 4 얼라이브 좀비로부터 탈출(Last 4 Alive: Escape From Zombies)","最終4生存: 逃脫殭屍(Last 4 Alive: Escape From Zombies)"],"publisher":"TROOOZE","releaseDate":20211014,"sizeInBytes":1621350154.24},{"id":"01006C50159C8000","names":["Zombie Is Planting","ゾンビ イズ プランティング","좀비 이즈 플랜팅(Zombie Is Planting)","殭屍在種植(Zombie Is Planting)"],"publisher":"TROOOZE","releaseDate":20211111,"sizeInBytes":552599552},{"id":"0100059015A96000","names":["7Days Origins","7デイズ オリジンズ","7데이즈 오리진스(7Days Origins)","7天起源(7Days Origins)"],"publisher":"TROOOZE","releaseDate":20250612,"sizeInBytes":169869312},{"id":"0100989016AE6000","names":["REDDEN: 100denarii","レッデン","레든(REDDEN)","雷登(REDDEN)"],"publisher":"TROOOZE","releaseDate":20220217,"sizeInBytes":765460480},{"id":"0100DAE016AEA000","names":["Space Stella: The Unknown Planet","スペースステラ 未知の惑星","스페이스 스텔라 미지의 행성(Space Stella: The Unknown Planet)","太空星球: 未知恒星(Space Stella: The Unknown Planet)"],"publisher":"TROOOZE","releaseDate":20220113,"sizeInBytes":3994319585.28},{"id":"01005C501749C000","names":["Counter Delta: The Bullet Rain","カウンターデルタ ザ・バレットレイン","카운터델타 더 불릿레인(Counter Delta: The Bullet Rain)","反三角部隊: 槍彈如雨(Counter Delta: The Bullet Rain)"],"publisher":"TROOOZE","releaseDate":20220303,"sizeInBytes":4015794421.76},{"id":"0100DD8017974000","names":["World War: Tank Battle","ワールドウォー タンクバトル","World War: Tank Battle(Guerre mondiale : bataille de chars)","월드워 탱크 배틀(World War: Tank Battle)","世界大戰: 坦克戰爭(World War: Tank Battle)"],"publisher":"TROOOZE","releaseDate":20220224,"sizeInBytes":1610612736},{"id":"01004D0017CCA000","names":["Dead Rain: New Zombie Virus","デッドレイン 新しいゾンビウイルス","데드레인 새로운 좀비 바이러스(Dead Rain: New Zombie Virus)","死雨: 新殭屍病毒(Dead Rain: New Zombie Virus)"],"publisher":"TROOOZE","releaseDate":20220915,"sizeInBytes":203423744},{"id":"0100E6B017F84000","names":["Space Genesis","スペースジェネシス","스페이스 제네시스(Space Genesis)","太空創世紀(Space Genesis)"],"publisher":"TROOOZE","releaseDate":20220421,"sizeInBytes":2093796556.8},{"id":"010019801868E000","names":["Haunted Zombie School","ホーンテッドゾンビ スクール","헌티드좀비 스쿨(Haunted Zombie School)","鬼魂殭屍校園(Haunted Zombie School)"],"publisher":"TROOOZE","releaseDate":20220616,"sizeInBytes":2759516487.68},{"id":"0100946018B80000","names":["Counter Recon 2: The New War","カウンターリーコン 2 ザ・ニューウォー","카운터리콘 2 더 뉴워(Counter Recon 2: The New War)","反偵察 2: 新戰爭(Counter Recon 2: The New War)"],"publisher":"TROOOZE","releaseDate":20220728,"sizeInBytes":2931315179.52},{"id":"0100FCC01920C000","names":["Modern War: Tank Battle","モダンウォー タンクバトル","모던워 탱크 배틀(Modern War: Tank Battle)","現代大戰: 坦克戰爭(Modern War: Tank Battle)"],"publisher":"TROOOZE","releaseDate":20220825,"sizeInBytes":1664299827.2},{"id":"010041E01949A000","names":["Counter Crossline: Crime War","カウンタークロスライン クライムウォー","카운터크로스라인 크라임 워(Counter Crossline: Crime War)","反交叉線: 犯罪戰爭(Counter Crossline: Crime War)"],"publisher":"TROOOZE","releaseDate":20220922,"sizeInBytes":2179695902.72},{"id":"010077F01949C000","names":["Bunker Life","バンカーライフ","벙커 라이프(Bunker Life)","地堡生活(Bunker Life)"],"publisher":"TROOOZE","releaseDate":20221006,"sizeInBytes":955252736},{"id":"010075F01989C000","names":["Car+Toon Race: Rally Valley Champion","カー+トゥーンレース ラリーバレーチャンピオン","카+툰레이스 랠리밸리 챔피언(Car+Toon Race: Rally Valley Champion)","動畫片賽車: 拉力賽山谷冠軍(Car+Toon Race: Rally Valley Champion)"],"publisher":"TROOOZE","releaseDate":20221027,"sizeInBytes":1428076625.92},{"id":"0100CD1019C50000","names":["World Class Champion Soccer","ワールドクラス チャンピオン サッカー","월드 클라쓰 챔피언 사커(World Class Champion Soccer)","世界級冠軍足球(World Class Champion Soccer)"],"publisher":"TROOOZE","releaseDate":20221117,"sizeInBytes":1771674009.6},{"id":"010097B01A0DE000","names":["Haunted Zombie Slaughter","ホーンテッドゾンビ スローター","헌티드좀비 슬로터(Haunted Zombie Slaughter)","鬼魂殭屍屠宰(Haunted Zombie Slaughter)"],"publisher":"TROOOZE","releaseDate":20230126,"sizeInBytes":2426656522.24},{"id":"01000A201A9F2000","names":["World War: Prologue","ワールドウォー プロローグ","월드워 프롤로그(World War: Prologue)","世界大戰 序章(World War: Prologue)"],"publisher":"TROOOZE","releaseDate":20230223,"sizeInBytes":2040109465.6},{"id":"0100AE401AEA8000","names":["Crime Busters: Strike Area","クライムバスターズ ストライク エリア","크라임버스터즈 스트라이크 에리어(Crime Busters: Strike Area)","犯罪巴斯特斯: 射擊區(Crime Busters: Strike Area)"],"publisher":"TROOOZE","releaseDate":20230323,"sizeInBytes":2673617141.76},{"id":"010003501B8F4000","names":["World War: Combat Guardian","ワールドウォー コンバットガーディアン","월드워 컴뱃가디언(World War: Combat Guardian)","世界大戰 戰鬥守護者(World War: Combat Guardian)"],"publisher":"TROOOZE","releaseDate":20230525,"sizeInBytes":2598455214.08},{"id":"01003E601C35E000","names":["Counter Delta 2: Eastern Crisis","カウンターデルタ 2 イースタン クライシス","카운터델타 2 이스턴 크라이시스(Counter Delta 2: Eastern Crisis)","反三角部隊 2: 東方危機(Counter Delta 2: Eastern Crisis)"],"publisher":"TROOOZE","releaseDate":20230727,"sizeInBytes":2576980377.6},{"id":"0100EC101CCCE000","names":["Adventure Word: Around the World","アドベンチャーワード アラウンド・ザ・ワールド","어드벤쳐 워드 어라운드 더 월드(Adventure Word: Around the World)","冒險單詞 環球旅行(Adventure Word: Around the World)"],"publisher":"TROOOZE","releaseDate":20231109,"sizeInBytes":598736896},{"id":"010037801CE28000","names":["The Legend of Shadow: Mask of the Force","レジェンドオブシャドウ マスクオブザフォース","레전드 오브 쉐도우 마스크 오브 더 포스(The Legend of Shadow: Mask of the Force)","影之傳說: 原力的面具(The Legend of Shadow: Mask of the Force)"],"publisher":"TROOOZE","releaseDate":20231012,"sizeInBytes":1309965025.28},{"id":"010094501CE96000","names":["Haunted Zombie Slaughter 2","ホーンテッドゾンビ スローター 2","헌티드좀비 슬로터 2(Haunted Zombie Slaughter 2)","鬼魂殭屍屠宰 2(Haunted Zombie Slaughter 2)"],"publisher":"TROOOZE","releaseDate":20230921,"sizeInBytes":2319282339.84},{"id":"01003DE01D52C000","names":["World War: D-Day PART ONE","ワールドウォー D-デイ PART ONE","월드워 디데이 PART ONE(World War: D-Day PART ONE)","世界大戰 D日上集(World War: D-Day PART ONE)"],"publisher":"TROOOZE","releaseDate":20231102,"sizeInBytes":2770253905.92},{"id":"010092D01D8FE000","names":["World War: D-Day PART TWO","ワールドウォー D-デイ PART TWO","월드워 디데이 PART TWO(World War: D-Day PART TWO)","世界大戰 D日下集(World War: D-Day PART TWO)"],"publisher":"TROOOZE","releaseDate":20231130,"sizeInBytes":1997159792.64},{"id":"0100BF401E1A4000","names":["Last 4 Survive: The Outbreak","ラスト4サバイブ アウトブレイク","라스트 4 서바이브 아웃브레이크(Last 4 Survive: The Outbreak)","最終4存活: 疫情爆發(Last 4 Survive: The Outbreak)"],"publisher":"TROOOZE","releaseDate":20240215,"sizeInBytes":1578400481.28},{"id":"010065101E814000","names":["Out Racing: Arcade Memory","アウトレーシング アーケードメモリー","아웃레이싱 오락실의 추억(Out Racing: Arcade Memory)","出跑賽車: 街機記憶(Out Racing: Arcade Memory)"],"publisher":"TROOOZE","releaseDate":20240328,"sizeInBytes":1954210119.68},{"id":"0100B0901EC0E000","names":["Alien Survivors: To Starship Resurrection","エイリアンサバイバーズ スターシップ レザレクション","에일리언 서바이버즈 스타쉽 레저렉션(Alien Survivors: To Starship Resurrection)","異形倖存者 星際飛船復活(Alien Survivors: To Starship Resurrection)"],"publisher":"TROOOZE","releaseDate":20240509,"sizeInBytes":620756992},{"id":"010009F01F05E000","names":["World War: Battle of the Bulge","ワールドウォー バルジの戦い","월드워 벌지 대전투(World War: Battle of the Bulge)","世界大戰 突出部之役(World War: Battle of the Bulge)"],"publisher":"TROOOZE","releaseDate":20240425,"sizeInBytes":2319282339.84},{"id":"010074301F654000","names":["Operation Scorpion: Take Down","オペレーションスコーピオン テイクダウン","오퍼레이션 스콜피온 테이크 다운(Operation Scorpion: Take Down)","作戰蝎子: 拿下(Operation Scorpion: Take Down)"],"publisher":"TROOOZE","releaseDate":20240530,"sizeInBytes":2716566814.72},{"id":"010098601F9BA000","names":["Urban Warfare: Assault","アーバンウォーフェア アサルト","어반 워페어 어썰트(Urban Warfare: Assault)","城市戰: 突擊(Urban Warfare: Assault)"],"publisher":"TROOOZE","releaseDate":20240711,"sizeInBytes":2695091978.24},{"id":"01009C001FDFC000","names":["Crazy Stars: Sport Climbing","クレイジースターズ スポーツクライミング","크레이지 스타즈 스포츠클라이밍(Crazy Stars: Sport Climbing)","瘋狂之星: 體育攀岩(Crazy Stars: Sport Climbing)"],"publisher":"TROOOZE","releaseDate":20240801,"sizeInBytes":1213328261.12},{"id":"0100BB0020008000","names":["World War: Fury Wave","ワールドウォー フューリー ウェーブ","월드워 퓨리 웨이브(World War: Fury Wave)","世界大戰 烈火戰車波(World War: Fury Wave)"],"publisher":"TROOOZE","releaseDate":20240822,"sizeInBytes":1395864371.2},{"id":"010047A020922000","names":["Gun Fire: AI Rebellion","ガンファイア AI リベリオン","건파이어 AI 리벨리언(Gun Fire: AI Rebellion)","槍火: 人工智慧叛亂(Gun Fire: AI Rebellion)"],"publisher":"TROOOZE","releaseDate":20241212,"sizeInBytes":644874240},{"id":"0100C930212A6000","names":["Anne's Zombie Odyssey","アンナのゾンビ オデッセイ","안나의 좀비 오디세이(Anne's Zombie Odyssey)","安娜的殭屍奧德賽(Anne's Zombie Odyssey)"],"publisher":"TROOOZE","releaseDate":20241128,"sizeInBytes":780140544},{"id":"01005DA020FAA000","names":["Sniper Jarhead","スナイパージャーヘッド","스나이퍼 자헤드(Sniper Jarhead)","狙擊手大頭兵(Sniper Jarhead)"],"publisher":"TROOOZE","releaseDate":20241121,"sizeInBytes":2147483648},{"id":"01002BA021ACA000","names":["District: Evolution","ディストリクト エボリューション","디스트릭트 에볼루션(District: Evolution)","區域: 進化(District: Evolution)"],"publisher":"TROOOZE","releaseDate":20250116,"sizeInBytes":3435973836.8},{"id":"01002470221B2000","names":["Exodus","エクソダス","엑소더스(Exodus)","出埃及記(Exodus)"],"publisher":"TROOOZE","releaseDate":20250206,"sizeInBytes":6281389670.4},{"id":"0100BA502285A000","names":["World At War: Normandy","ワールド アット ウォー ノルマンディー","월드 앳 워 노르망디(World At War: Normandy)","世界大戰: 諾曼第登陸(World At War: Normandy)"],"publisher":"TROOOZE","releaseDate":20250227,"sizeInBytes":3639984783.36},{"id":"01002DB022B16000","names":["Special Warfare","스페셜 워페어(Special Warfare)","特殊戰爭(Special Warfare)"],"publisher":"TROOOZE","releaseDate":20250327,"sizeInBytes":4907000135.68},{"id":"01002D2022FCC000","names":["Strange Hunting Grounds","イカれた狩り場の看板娘","이상한 사냥터(Strange Hunting Grounds)","瘋狂的狩獵場招牌娘(Strange Hunting Grounds)"],"publisher":"TROOOZE","releaseDate":20250619,"sizeInBytes":1202590842.88},{"id":"010056802454C000","names":["Combat Strike","コンバット ストライク","컴뱃 스트라이크(Combat Strike)","戰鬥突擊(Combat Strike)"],"publisher":"TROOOZE","releaseDate":20250724,"sizeInBytes":4853313044.48},{"id":"0100AA9011238000","names":["애니머스(ANIMUS)","ANIMUS"],"publisher":"TROOOZE","releaseDate":20230126,"sizeInBytes":2018634629.12},{"id":"010028301123A000","names":["애니머스 하빈저(ANIMUS: Harbinger)","ANIMUS: Harbinger"],"publisher":"TROOOZE","releaseDate":20230126,"sizeInBytes":1728724336.64},{"id":"010073A02398C000","names":["스페셜 스트라이크(Special Strike)","特種突擊(Special Strike)"],"publisher":"TROOOZE","releaseDate":20250529,"sizeInBytes":5175435591.68}]